vibevoice/__init__.py
vibevoice/modular/__init__.py
vibevoice/modular/configuration_vibevoice.py
vibevoice/modular/modeling_vibevoice.py
vibevoice/modular/modeling_vibevoice_inference.py
vibevoice/modular/modular_vibevoice_diffusion_head.py
vibevoice/modular/modular_vibevoice_text_tokenizer.py
vibevoice/modular/modular_vibevoice_tokenizer.py
vibevoice/modular/streamer.py
vibevoice/processor/__init__.py
vibevoice/processor/vibevoice_processor.py
vibevoice/processor/vibevoice_tokenizer_processor.py
vibevoice/schedule/__init__.py
vibevoice/schedule/dpm_solver.py
vibevoice/schedule/timestep_sampler.py
vibevoice/scripts/__init__.py
vibevoice/scripts/convert_nnscaler_checkpoint_to_transformers.py
voicebridge/__init__.py
voicebridge/__main__.py
voicebridge/main.py
voicebridge/adapters/__init__.py
voicebridge/adapters/api_endpoints.py
voicebridge/adapters/audio.py
voicebridge/adapters/audio_factory.py
voicebridge/adapters/audio_formats.py
voicebridge/adapters/audio_playback.py
voicebridge/adapters/audio_preprocessing.py
voicebridge/adapters/audio_splitting.py
voicebridge/adapters/circuit_breaker.py
voicebridge/adapters/config.py
voicebridge/adapters/logging.py
voicebridge/adapters/session.py
voicebridge/adapters/system.py
voicebridge/adapters/text_input.py
voicebridge/adapters/transcription.py
voicebridge/adapters/vibevoice_tts.py
voicebridge/adapters/vocabulary.py
voicebridge/adapters/wsl_audio.py
voicebridge/adapters/text_processors/__init__.py
voicebridge/adapters/text_processors/capitalization_processor.py
voicebridge/adapters/text_processors/profanity_filter.py
voicebridge/adapters/text_processors/punctuation_processor.py
voicebridge/cli/__init__.py
voicebridge/cli/app.py
voicebridge/cli/registry.py
voicebridge/cli/commands/__init__.py
voicebridge/cli/commands/advanced_commands.py
voicebridge/cli/commands/api_commands.py
voicebridge/cli/commands/audio_commands.py
voicebridge/cli/commands/base.py
voicebridge/cli/commands/config_commands.py
voicebridge-0.0.1.dist-info/licenses/LICENSE
voicebridge-0.0.1.dist-info/METADATA
voicebridge-0.0.1.dist-info/WHEEL
voicebridge-0.0.1.dist-info/entry_points.txt
voicebridge-0.0.1.dist-info/top_level.txt
voicebridge-0.0.1.dist-info/RECORD
