Metadata-Version: 2.4
Name: voicebridge
Version: 0.0.1
Summary: Comprehensive bidirectional voice-text CLI tool with Whisper and VibeVoice
Author: Patrick
License-Expression: MIT
Classifier: Development Status :: 4 - Beta
Classifier: Intended Audience :: Developers
Classifier: Topic :: Multimedia :: Sound/Audio :: Speech
Classifier: Programming Language :: Python :: 3
Classifier: Programming Language :: Python :: 3.11
Classifier: Programming Language :: Python :: 3.12
Requires-Python: >=3.11
License-File: LICENSE
Requires-Dist: typer>=0.16.0
Requires-Dist: rich>=14.0.0
Requires-Dist: pydantic>=2.11.0
Requires-Dist: PyYAML>=6.0.2
Requires-Dist: openai-whisper>=20250625
Requires-Dist: pygame>=2.6.1
Requires-Dist: setuptools<81,>=70.0.0
Requires-Dist: PyAudio>=0.2.14
Requires-Dist: soundfile>=0.13.1
Requires-Dist: librosa>=0.11.0
Requires-Dist: noisereduce>=3.0.3
Requires-Dist: pydub>=0.25.1
Requires-Dist: ffmpy>=0.6.1
Requires-Dist: torch>=2.8.0
Requires-Dist: torchaudio>=2.8.0
Requires-Dist: torchvision>=0.23.0
Requires-Dist: torchmetrics>=1.8.2
Requires-Dist: transformers==4.51.3
Requires-Dist: accelerate>=1.10.1
Requires-Dist: diffusers>=0.35.1
Requires-Dist: safetensors>=0.6.2
Requires-Dist: tiktoken>=0.11.0
Requires-Dist: tokenizers>=0.21.4
Requires-Dist: anyascii>=0.3.2
Requires-Dist: coqpit>=0.0.17
Requires-Dist: encodec>=0.1.1
Requires-Dist: ml-collections>=0.1.1
Requires-Dist: absl-py>=2.0.0
Requires-Dist: av>=13.1.0
Requires-Dist: aiortc>=1.9.0
Requires-Dist: numba>=0.57.0
Requires-Dist: llvmlite>=0.40.0
Requires-Dist: gradio>=5.0.0
Requires-Dist: pynput>=1.8.1
Requires-Dist: pyperclip>=1.9.0
Requires-Dist: psutil>=7.0.0
Requires-Dist: python-xlib>=0.33; sys_platform == "linux"
Requires-Dist: evdev>=1.9.2; sys_platform == "linux"
Requires-Dist: fastapi>=0.116.1
Requires-Dist: uvicorn>=0.35.0
Requires-Dist: httpx>=0.28.1
Requires-Dist: aiohttp>=3.8.0
Requires-Dist: aiofiles>=24.1.0
Requires-Dist: websockets>=15.0.1
Requires-Dist: numpy>=2.2.6
Requires-Dist: pandas>=2.3.2
Requires-Dist: scipy>=1.16.2
Requires-Dist: scikit-learn>=1.7.2
Requires-Dist: python-dateutil>=2.9.0
Requires-Dist: tqdm>=4.67.1
Requires-Dist: joblib>=1.5.1
Requires-Dist: filelock>=3.18.0
Requires-Dist: packaging>=25.0
Requires-Dist: certifi>=2025.6.15
Requires-Dist: requests>=2.32.4
Requires-Dist: beautifulsoup4>=4.13.4
Requires-Dist: huggingface_hub[hf_xet]
Provides-Extra: dev
Requires-Dist: pytest>=8.4.2; extra == "dev"
Requires-Dist: pytest-cov>=6.3.0; extra == "dev"
Requires-Dist: pytest-mock>=3.15.0; extra == "dev"
Requires-Dist: pytest-asyncio>=0.21.0; extra == "dev"
Requires-Dist: ruff>=0.1.15; extra == "dev"
Requires-Dist: black>=25.1.0; extra == "dev"
Requires-Dist: coverage>=7.10.6; extra == "dev"
Provides-Extra: cuda
Requires-Dist: torch>=2.8.0; extra == "cuda"
Requires-Dist: torchaudio>=2.8.0; extra == "cuda"
Requires-Dist: torchvision>=0.23.0; extra == "cuda"
Requires-Dist: triton>=3.4.0; extra == "cuda"
Provides-Extra: tray
Requires-Dist: pystray>=0.19.4; extra == "tray"
Requires-Dist: Pillow>=11.2.1; extra == "tray"
Dynamic: license-file
